tests/__init__.py
tests/core/__init__.py
tests/core/test_app.py
vbet/__init__.py
vbet/core/__init__.py
vbet/core/app.py
vbet/core/session.py
vbet/core/settings.py
vbet/core/user_manager.py
vbet/core/vbet.py
vbet/core/vshell.py
vbet/core/ws_server.py
vbet/game/__init__.py
vbet/game/accounts.py
vbet/game/competition.py
vbet/game/markets.py
vbet/game/socket.py
vbet/game/table.py
vbet/game/tickets.py
vbet/game/user.py
vbet/game/api/__init__.py
vbet/game/api/auth.py
vbet/game/players/__init__.py
vbet/game/players/base.py
vbet/game/players/dybala.py
vbet/game/players/fati.py
vbet/game/players/hazard.py
vbet/game/players/mbape.py
vbet/game/players/messi.py
vbet/game/players/neymar.py
vbet/game/players/ozil.py
vbet/game/players/puig.py
vbet/game/players/ronaldo.py
vbet/game/players/rooney.py
vbet/game/players/salah.py
vbet/game/players/xavi.py
vbet/utils/__init__.py
vbet/utils/exceptions.py
vbet/utils/log.py
vbet/utils/logger.py
vbet/utils/parser.py
vbet-6.20.4.data/scripts/vrun
vbet-6.20.4.data/scripts/vshell
vbet-6.20.4.dist-info/LICENSE
vbet-6.20.4.dist-info/METADATA
vbet-6.20.4.dist-info/WHEEL
vbet-6.20.4.dist-info/top_level.txt
vbet-6.20.4.dist-info/RECORD
