Metadata-Version: 2.1
Name: vbet
Version: 6.20.4
Summary: A virtual betting bot server
Home-page: https://github.com/updatedennismwangi/vbet.git
Author: Dennis Mwangi
Author-email: updatedennismwangi@gmail.com
License: UNKNOWN
Platform: UNKNOWN
Classifier: Programming Language :: Python :: 3.8
Classifier: Operating System :: Unix
Classifier: License :: OSI Approved :: GNU General Public License v3 (GPLv3)
Requires-Python: >=3.6
Requires-Dist: aiofile (==3.0.0)
Requires-Dist: aiohttp (==3.6.2)
Requires-Dist: aioredis (==1.3.1)
Requires-Dist: pytz (==2020.1)
Requires-Dist: websockets (==8.1)
Requires-Dist: asynccmd (~=0.2.4)
Requires-Dist: setuptools (~=49.3.2)
Requires-Dist: pytest (~=6.0.1)
